{
    "best_params": {
        "activation": "tanh",
        "batch_size": 25,
        "dropout_rate": 0.2,
        "epochs": 100,
        "learning_rate": 0.0001,
        "num_lstm_layers": 1,
        "units_lstm": 128
    },
    "look_back": 15,
    "evaluation": {
        "mae": 0.012660329230129719,
        "rmse": 0.01692992076277733
    },
    "results": {
        "true_values": [
            [
                0.30343201756477356
            ],
            [
                0.3190919756889343
            ],
            [
                0.3550280034542084
            ],
            [
                0.38080400228500366
            ],
            [
                0.4254719913005829
            ],
            [
                0.3884999752044678
            ],
            [
                0.3442400097846985
            ],
            [
                0.3250720202922821
            ],
            [
                0.3185119926929474
            ],
            [
                0.2863040268421173
            ],
            [
                0.31858399510383606
            ],
            [
                0.30087199807167053
            ],
            [
                0.32375597953796387
            ],
            [
                0.2901719808578491
            ],
            [
                0.24567200243473053
            ],
            [
                0.22114799916744232
            ],
            [
                0.19397199153900146
            ],
            [
                0.194240003824234
            ],
            [
                0.1558760106563568
            ],
            [
                0.130063995718956
            ],
            [
                0.10605199635028839
            ],
            [
                0.08381599187850952
            ],
            [
                0.05565999820828438
            ],
            [
                0.030291998758912086
            ],
            [
                0.03102799691259861
            ],
            [
                0.014388004317879677
            ],
            [
                0.015751997008919716
            ],
            [
                0.014051998034119606
            ],
            [
                0.014920005574822426
            ],
            [
                0.014615992084145546
            ],
            [
                0.018799999728798866
            ],
            [
                0.01799199916422367
            ],
            [
                0.02051999606192112
            ],
            [
                0.02131999470293522
            ],
            [
                0.01881999708712101
            ],
            [
                0.02099599875509739
            ],
            [
                0.020219990983605385
            ],
            [
                0.019123995676636696
            ],
            [
                0.030764000490307808
            ],
            [
                0.03527599200606346
            ],
            [
                0.054072003811597824
            ],
            [
                0.07759600132703781
            ],
            [
                0.12505599856376648
            ],
            [
                0.21348801255226135
            ],
            [
                0.24969598650932312
            ],
            [
                0.29811200499534607
            ],
            [
                0.27721598744392395
            ],
            [
                0.31526002287864685
            ],
            [
                0.33560001850128174
            ],
            [
                0.3387719690799713
            ],
            [
                0.3582800030708313
            ],
            [
                0.42024800181388855
            ],
            [
                0.3790919780731201
            ],
            [
                0.33918800950050354
            ],
            [
                0.3530239760875702
            ],
            [
                0.30878397822380066
            ],
            [
                0.26023200154304504
            ],
            [
                0.22956399619579315
            ],
            [
                0.22553998231887817
            ],
            [
                0.20052799582481384
            ],
            [
                0.1763320118188858
            ],
            [
                0.18728400766849518
            ],
            [
                0.17659999430179596
            ],
            [
                0.1620439887046814
            ],
            [
                0.12931598722934723
            ],
            [
                0.12834800779819489
            ],
            [
                0.09729999303817749
            ],
            [
                0.045903999358415604
            ],
            [
                0.04728400334715843
            ],
            [
                0.03638399764895439
            ],
            [
                0.01964799501001835
            ],
            [
                0.017495999112725258
            ],
            [
                0.020007992163300514
            ],
            [
                0.011371994391083717
            ],
            [
                0.014399999752640724
            ],
            [
                0.013496005907654762
            ],
            [
                0.014268005266785622
            ],
            [
                0.015556002035737038
            ],
            [
                0.015331992879509926
            ],
            [
                0.015603998675942421
            ],
            [
                0.017671996727585793
            ],
            [
                0.027351999655365944
            ],
            [
                0.036072004586458206
            ],
            [
                0.0380840040743351
            ],
            [
                0.04630399867892265
            ],
            [
                0.06043200567364693
            ],
            [
                0.09669199585914612
            ],
            [
                0.08936398476362228
            ],
            [
                0.09781200438737869
            ],
            [
                0.20758399367332458
            ],
            [
                0.22836799919605255
            ],
            [
                0.2390960156917572
            ],
            [
                0.31610798835754395
            ],
            [
                0.29903197288513184
            ],
            [
                0.38311198353767395
            ],
            [
                0.3643440008163452
            ],
            [
                0.3502799868583679
            ],
            [
                0.3523840010166168
            ],
            [
                0.3689839839935303
            ],
            [
                0.3581159710884094
            ],
            [
                0.34463199973106384
            ],
            [
                0.28320398926734924
            ],
            [
                0.307888001203537
            ],
            [
                0.2760399878025055
            ],
            [
                0.27649998664855957
            ],
            [
                0.30464401841163635
            ],
            [
                0.27400001883506775
            ],
            [
                0.23379197716712952
            ],
            [
                0.23143598437309265
            ],
            [
                0.18541599810123444
            ],
            [
                0.15561600029468536
            ],
            [
                0.1395760029554367
            ],
            [
                0.11175999790430069
            ],
            [
                0.08394800126552582
            ],
            [
                0.05518799647688866
            ],
            [
                0.03275199607014656
            ],
            [
                0.02603999711573124
            ],
            [
                0.02633599378168583
            ],
            [
                0.021672004833817482
            ],
            [
                0.02117999829351902
            ],
            [
                0.019644001498818398
            ],
            [
                0.017111996188759804
            ],
            [
                0.01768399216234684
            ],
            [
                0.023080000653862953
            ],
            [
                0.017747992649674416
            ],
            [
                0.021368006244301796
            ],
            [
                0.029175998643040657
            ],
            [
                0.029316002503037453
            ],
            [
                0.037963997572660446
            ],
            [
                0.03502799943089485
            ],
            [
                0.048247989267110825
            ],
            [
                0.08909998834133148
            ],
            [
                0.08435999602079391
            ],
            [
                0.11061200499534607
            ],
            [
                0.16662399470806122
            ],
            [
                0.21433599293231964
            ],
            [
                0.26380398869514465
            ],
            [
                0.2677919864654541
            ],
            [
                0.2787719964981079
            ],
            [
                0.36489197611808777
            ],
            [
                0.3739839792251587
            ],
            [
                0.328575998544693
            ],
            [
                0.3240240216255188
            ],
            [
                0.3522319793701172
            ],
            [
                0.3632839620113373
            ],
            [
                0.37530001997947693
            ],
            [
                0.319815993309021
            ],
            [
                0.2902040183544159
            ],
            [
                0.25722798705101013
            ],
            [
                0.2622919976711273
            ],
            [
                0.22779998183250427
            ],
            [
                0.24273601174354553
            ],
            [
                0.20833998918533325
            ],
            [
                0.23900799453258514
            ],
            [
                0.22479599714279175
            ],
            [
                0.1711519956588745
            ],
            [
                0.13411200046539307
            ],
            [
                0.12194398790597916
            ],
            [
                0.10074799507856369
            ],
            [
                0.06301199644804001
            ],
            [
                0.0529320053756237
            ],
            [
                0.04786800220608711
            ],
            [
                0.034679997712373734
            ],
            [
                0.02287999726831913
            ],
            [
                0.01521199382841587
            ],
            [
                0.015511998906731606
            ],
            [
                0.018507996574044228
            ],
            [
                0.009004006162285805
            ],
            [
                0.013876000419259071
            ],
            [
                0.013940000906586647
            ],
            [
                0.014048004522919655
            ],
            [
                0.0169800017029047
            ],
            [
                0.012724006548523903
            ],
            [
                0.005499998573213816
            ],
            [
                0.04145600274205208
            ],
            [
                0.040608000010252
            ],
            [
                0.04402400180697441
            ],
            [
                0.04177199676632881
            ],
            [
                0.08703199028968811
            ],
            [
                0.10674799978733063
            ],
            [
                0.11139199882745743
            ],
            [
                0.14380401372909546
            ],
            [
                0.17709998786449432
            ],
            [
                0.19349201023578644
            ],
            [
                0.22735999524593353
            ],
            [
                0.31187599897384644
            ],
            [
                0.3905639946460724
            ],
            [
                0.30986401438713074
            ],
            [
                0.4000200033187866
            ],
            [
                0.3305719792842865
            ],
            [
                0.36821597814559937
            ],
            [
                0.3621160089969635
            ],
            [
                0.33070001006126404
            ],
            [
                0.3472999930381775
            ],
            [
                0.33205196261405945
            ],
            [
                0.32622799277305603
            ],
            [
                0.311924010515213
            ],
            [
                0.30035197734832764
            ],
            [
                0.27763599157333374
            ],
            [
                0.24721597135066986
            ],
            [
                0.19176000356674194
            ],
            [
                0.18067599833011627
            ],
            [
                0.15319599211215973
            ],
            [
                0.1368200033903122
            ],
            [
                0.11600399762392044
            ],
            [
                0.09948799759149551
            ],
            [
                0.04622800275683403
            ],
            [
                0.03494800254702568
            ],
            [
                0.02473999746143818
            ],
            [
                0.015919992700219154
            ],
            [
                0.016088003292679787
            ],
            [
                0.017407992854714394
            ],
            [
                0.014736006036400795
            ]
        ],
        "predicted_values": [
            [
                0.3126011788845062
            ],
            [
                0.3374969959259033
            ],
            [
                0.3673672676086426
            ],
            [
                0.34725165367126465
            ],
            [
                0.3864322900772095
            ],
            [
                0.3743442893028259
            ],
            [
                0.34955382347106934
            ],
            [
                0.34754759073257446
            ],
            [
                0.3320918083190918
            ],
            [
                0.29445502161979675
            ],
            [
                0.29697471857070923
            ],
            [
                0.2724074721336365
            ],
            [
                0.26982051134109497
            ],
            [
                0.25641006231307983
            ],
            [
                0.22467748820781708
            ],
            [
                0.20065996050834656
            ],
            [
                0.17495277523994446
            ],
            [
                0.15678443014621735
            ],
            [
                0.1300031691789627
            ],
            [
                0.11185120791196823
            ],
            [
                0.09960184246301651
            ],
            [
                0.0750201940536499
            ],
            [
                0.055334556847810745
            ],
            [
                0.03469006344676018
            ],
            [
                0.024110982194542885
            ],
            [
                0.015815624967217445
            ],
            [
                0.009364033117890358
            ],
            [
                0.010288545861840248
            ],
            [
                0.010835984721779823
            ],
            [
                0.014827931299805641
            ],
            [
                0.016834625974297523
            ],
            [
                0.014407912269234657
            ],
            [
                0.016810500994324684
            ],
            [
                0.022175783291459084
            ],
            [
                0.01875264383852482
            ],
            [
                0.016784245148301125
            ],
            [
                0.01275513507425785
            ],
            [
                0.011277580633759499
            ],
            [
                0.02689063735306263
            ],
            [
                0.026566730812191963
            ],
            [
                0.031436968594789505
            ],
            [
                0.05338738486170769
            ],
            [
                0.09294836968183517
            ],
            [
                0.16358840465545654
            ],
            [
                0.21775633096694946
            ],
            [
                0.2777315676212311
            ],
            [
                0.28568893671035767
            ],
            [
                0.3426920473575592
            ],
            [
                0.35901328921318054
            ],
            [
                0.3564300239086151
            ],
            [
                0.3770088255405426
            ],
            [
                0.3895965814590454
            ],
            [
                0.3555954694747925
            ],
            [
                0.322755366563797
            ],
            [
                0.2993474006652832
            ],
            [
                0.2682645320892334
            ],
            [
                0.25577813386917114
            ],
            [
                0.24638418853282928
            ],
            [
                0.23395463824272156
            ],
            [
                0.22394660115242004
            ],
            [
                0.19581352174282074
            ],
            [
                0.189651757478714
            ],
            [
                0.17451931536197662
            ],
            [
                0.16125120222568512
            ],
            [
                0.14157487452030182
            ],
            [
                0.12181821465492249
            ],
            [
                0.09695099294185638
            ],
            [
                0.0726633220911026
            ],
            [
                0.054641108959913254
            ],
            [
                0.040842894464731216
            ],
            [
                0.024765627458691597
            ],
            [
                0.021516600623726845
            ],
            [
                0.0201870147138834
            ],
            [
                0.0067602344788610935
            ],
            [
                0.012790733948349953
            ],
            [
                0.008613521233201027
            ],
            [
                0.01079089380800724
            ],
            [
                0.011244604364037514
            ],
            [
                0.006787205580621958
            ],
            [
                0.011084431782364845
            ],
            [
                0.012665921822190285
            ],
            [
                0.020676264539361
            ],
            [
                0.028529131785035133
            ],
            [
                0.03947940096259117
            ],
            [
                0.044527601450681686
            ],
            [
                0.05064361169934273
            ],
            [
                0.07736830413341522
            ],
            [
                0.10165855288505554
            ],
            [
                0.11322034150362015
            ],
            [
                0.18014109134674072
            ],
            [
                0.21545305848121643
            ],
            [
                0.24439342319965363
            ],
            [
                0.29397034645080566
            ],
            [
                0.306922972202301
            ],
            [
                0.34461885690689087
            ],
            [
                0.3625281751155853
            ],
            [
                0.3333633244037628
            ],
            [
                0.37532439827919006
            ],
            [
                0.3887940049171448
            ],
            [
                0.37709295749664307
            ],
            [
                0.35406553745269775
            ],
            [
                0.3282177150249481
            ],
            [
                0.30636340379714966
            ],
            [
                0.27833443880081177
            ],
            [
                0.2781285047531128
            ],
            [
                0.278031587600708
            ],
            [
                0.24217788875102997
            ],
            [
                0.20951434969902039
            ],
            [
                0.18824850022792816
            ],
            [
                0.15944384038448334
            ],
            [
                0.13603654503822327
            ],
            [
                0.11972165107727051
            ],
            [
                0.10146629810333252
            ],
            [
                0.08640657365322113
            ],
            [
                0.06617031246423721
            ],
            [
                0.04042618349194527
            ],
            [
                0.02811662293970585
            ],
            [
                0.020288819447159767
            ],
            [
                0.013108635321259499
            ],
            [
                0.013658309355378151
            ],
            [
                0.013192245736718178
            ],
            [
                0.00907757319509983
            ],
            [
                0.01115516759455204
            ],
            [
                0.017172077670693398
            ],
            [
                0.014038095250725746
            ],
            [
                0.0211357269436121
            ],
            [
                0.020222404971718788
            ],
            [
                0.026418017223477364
            ],
            [
                0.03781968727707863
            ],
            [
                0.046385277062654495
            ],
            [
                0.049468863755464554
            ],
            [
                0.07536812871694565
            ],
            [
                0.08723331242799759
            ],
            [
                0.10413342714309692
            ],
            [
                0.16151799261569977
            ],
            [
                0.21338088810443878
            ],
            [
                0.2532409131526947
            ],
            [
                0.2760986387729645
            ],
            [
                0.2971944808959961
            ],
            [
                0.3443964421749115
            ],
            [
                0.3662647008895874
            ],
            [
                0.3397994637489319
            ],
            [
                0.343877911567688
            ],
            [
                0.3585469424724579
            ],
            [
                0.3619203269481659
            ],
            [
                0.3615974485874176
            ],
            [
                0.32841846346855164
            ],
            [
                0.3013584613800049
            ],
            [
                0.27215296030044556
            ],
            [
                0.28092244267463684
            ],
            [
                0.2569688558578491
            ],
            [
                0.25014373660087585
            ],
            [
                0.21991874277591705
            ],
            [
                0.21744416654109955
            ],
            [
                0.2011483758687973
            ],
            [
                0.17272451519966125
            ],
            [
                0.1477338671684265
            ],
            [
                0.12386628240346909
            ],
            [
                0.0957285687327385
            ],
            [
                0.07706163078546524
            ],
            [
                0.06201658025383949
            ],
            [
                0.045668233186006546
            ],
            [
                0.02806195057928562
            ],
            [
                0.017847323790192604
            ],
            [
                0.015245804563164711
            ],
            [
                0.012678602710366249
            ],
            [
                0.014111706987023354
            ],
            [
                0.009058037772774696
            ],
            [
                0.011097127571702003
            ],
            [
                0.005712414626032114
            ],
            [
                0.009015941992402077
            ],
            [
                0.007635334972292185
            ],
            [
                0.015293652191758156
            ],
            [
                0.009951600804924965
            ],
            [
                0.03499344363808632
            ],
            [
                0.04055790975689888
            ],
            [
                0.046242307871580124
            ],
            [
                0.039382804185152054
            ],
            [
                0.061569567769765854
            ],
            [
                0.09242946654558182
            ],
            [
                0.10856573283672333
            ],
            [
                0.14122937619686127
            ],
            [
                0.18790140748023987
            ],
            [
                0.21446089446544647
            ],
            [
                0.2637863755226135
            ],
            [
                0.2977873384952545
            ],
            [
                0.3570953905582428
            ],
            [
                0.335881769657135
            ],
            [
                0.3852517902851105
            ],
            [
                0.35047709941864014
            ],
            [
                0.35492441058158875
            ],
            [
                0.34758228063583374
            ],
            [
                0.3145633637905121
            ],
            [
                0.3713199198246002
            ],
            [
                0.3410314917564392
            ],
            [
                0.3395027220249176
            ],
            [
                0.31504493951797485
            ],
            [
                0.28449347615242004
            ],
            [
                0.2594531178474426
            ],
            [
                0.23435503244400024
            ],
            [
                0.19472429156303406
            ],
            [
                0.17282290756702423
            ],
            [
                0.1412086933851242
            ],
            [
                0.11067919433116913
            ],
            [
                0.08847840875387192
            ],
            [
                0.06437046080827713
            ],
            [
                0.044648800045251846
            ],
            [
                0.030162299051880836
            ],
            [
                0.021254608407616615
            ],
            [
                0.017192402854561806
            ],
            [
                0.013488570228219032
            ],
            [
                0.009357089176774025
            ],
            [
                0.012706229463219643
            ]
        ]
    },
    "history": {
        "loss": [
            1.0210065841674805,
            0.5979575514793396,
            0.41000738739967346,
            0.29396966099739075,
            0.22186514735221863,
            0.16858495771884918,
            0.13991454243659973,
            0.1189422756433487,
            0.10920564830303192,
            0.10562764108181,
            0.09173043817281723,
            0.08663418889045715,
            0.08500482141971588,
            0.08936409652233124,
            0.083309605717659,
            0.07934585213661194,
            0.07784731686115265,
            0.06661480665206909,
            0.07135208696126938,
            0.06894512474536896,
            0.07969194650650024,
            0.07671011984348297,
            0.06642165035009384,
            0.07009471207857132,
            0.06816424429416656,
            0.06123311445116997,
            0.07093529403209686,
            0.06040263921022415,
            0.06544632464647293,
            0.06140747666358948,
            0.053804051131010056,
            0.060387011617422104,
            0.05846940353512764,
            0.061839159578084946,
            0.0599212571978569,
            0.054278664290905,
            0.06055746227502823,
            0.06374754756689072,
            0.054354362189769745,
            0.05920237675309181,
            0.05300304666161537,
            0.0559077113866806,
            0.051668308675289154,
            0.05339890345931053,
            0.0529249869287014,
            0.05453984811902046,
            0.05254490673542023,
            0.05006372183561325,
            0.049481380730867386,
            0.04364698752760887,
            0.04640241712331772,
            0.045573871582746506,
            0.04270163178443909,
            0.04486584663391113,
            0.04161449521780014,
            0.0446702316403389,
            0.04292672500014305,
            0.04616496339440346,
            0.04267163202166557,
            0.037648335099220276,
            0.0448230504989624,
            0.04287388548254967,
            0.04415832459926605,
            0.03713322803378105,
            0.03578256443142891,
            0.03790770098567009,
            0.036779485642910004,
            0.03035244159400463,
            0.04181383550167084,
            0.034928034991025925,
            0.03703123703598976,
            0.037071600556373596,
            0.03642409294843674,
            0.035421907901763916,
            0.03398262709379196,
            0.0312514565885067,
            0.03673485293984413,
            0.031016599386930466,
            0.030239252373576164,
            0.030056625604629517,
            0.03253638371825218,
            0.0294643547385931,
            0.028726685792207718,
            0.03140508383512497,
            0.027745656669139862,
            0.031836822628974915,
            0.029619941487908363,
            0.02868734300136566,
            0.03321249037981033,
            0.03053996153175831,
            0.02806634083390236,
            0.025406764820218086,
            0.030816618353128433,
            0.02981674298644066,
            0.030485281720757484,
            0.026857076212763786,
            0.03413882479071617,
            0.02993868850171566,
            0.02525727078318596,
            0.029030868783593178
        ],
        "val_loss": [
            0.6263424754142761,
            0.39175936579704285,
            0.26029807329177856,
            0.1587473601102829,
            0.08598201721906662,
            0.043906040489673615,
            0.024367988109588623,
            0.01576356403529644,
            0.013402276672422886,
            0.012074734084308147,
            0.011930986307561398,
            0.013825437054038048,
            0.016882766038179398,
            0.014395068399608135,
            0.014100153930485249,
            0.016129137948155403,
            0.015868525952100754,
            0.01698351465165615,
            0.01660395786166191,
            0.017629729583859444,
            0.016800902783870697,
            0.01808062568306923,
            0.019978536292910576,
            0.018642667680978775,
            0.01897459290921688,
            0.019170429557561874,
            0.018516631796956062,
            0.017225533723831177,
            0.018850864842534065,
            0.018831269815564156,
            0.018735770136117935,
            0.02058323100209236,
            0.020293058827519417,
            0.021420350298285484,
            0.022417396306991577,
            0.019533313810825348,
            0.019738731905817986,
            0.01871953345835209,
            0.021286575123667717,
            0.019292118027806282,
            0.021609269082546234,
            0.02199966460466385,
            0.021857013925909996,
            0.0236875768750906,
            0.02278006263077259,
            0.023326409980654716,
            0.022758493199944496,
            0.02358996495604515,
            0.0207666028290987,
            0.02394135668873787,
            0.024909917265176773,
            0.02422228828072548,
            0.02198631688952446,
            0.023398607969284058,
            0.020052116364240646,
            0.01941065862774849,
            0.018420284613966942,
            0.020778222009539604,
            0.020215092226862907,
            0.019815366715192795,
            0.021818412467837334,
            0.022505762055516243,
            0.02200978249311447,
            0.025504888966679573,
            0.022935787215828896,
            0.020381616428494453,
            0.02128903940320015,
            0.01948167197406292,
            0.022941963747143745,
            0.02040291205048561,
            0.020349863916635513,
            0.02328251115977764,
            0.0224931500852108,
            0.022200901061296463,
            0.022705072537064552,
            0.02111407183110714,
            0.023730307817459106,
            0.022830234840512276,
            0.02207118272781372,
            0.022801611572504044,
            0.022372331470251083,
            0.023576922714710236,
            0.022118883207440376,
            0.020219385623931885,
            0.020737353712320328,
            0.02022845484316349,
            0.020263854414224625,
            0.023453691974282265,
            0.022402163594961166,
            0.019487835466861725,
            0.02035319246351719,
            0.020379211753606796,
            0.02131838910281658,
            0.020525513216853142,
            0.021563204005360603,
            0.022641455754637718,
            0.02185204066336155,
            0.022515445947647095,
            0.019300827756524086,
            0.01989469677209854
        ]
    }
}